viewsource/__init__.py
viewsource-3.12.0.dist-info/METADATA
viewsource-3.12.0.dist-info/WHEEL
viewsource-3.12.0.dist-info/top_level.txt
viewsource-3.12.0.dist-info/RECORD
